collectmeterdigits/__init__.py
collectmeterdigits/__main__.py
collectmeterdigits/collect.py
collectmeterdigits/glob.py
collectmeterdigits/hash_manual.py
collectmeterdigits/labeling.py
collectmeterdigits/predict.py
collectmeterdigits/models/dig-class100-0160_s2_q.tflite
collectmeterdigits-1.0.10.dist-info/LICENSE
collectmeterdigits-1.0.10.dist-info/METADATA
collectmeterdigits-1.0.10.dist-info/WHEEL
collectmeterdigits-1.0.10.dist-info/top_level.txt
collectmeterdigits-1.0.10.dist-info/RECORD
